mood/__init__.py
mood/dataset_makers.py
mood/learn_sentiments.py
mood/model_analysis.py
mood/mood_modeling.py
mood/sentiment.py
mood/tools.py
mood/util.py
mood/data/financial_news_search_words.json
mood/examples/__init__.py
mood/scripts/__init__.py
mood/scripts/financial_news_searches.py
mood-0.0.15.dist-info/LICENSE
mood-0.0.15.dist-info/METADATA
mood-0.0.15.dist-info/WHEEL
mood-0.0.15.dist-info/entry_points.txt
mood-0.0.15.dist-info/top_level.txt
mood-0.0.15.dist-info/RECORD
