Metadata-Version: 2.1
Name: mood
Version: 0.0.15
Summary: Investigations in financial sentiment analysis
Home-page: https://github.com/infinvest/mood
License: mit
Keywords: finance,trading,sentiment analysis,web scraping,nlp,text analysis
Platform: any
License-File: LICENSE
Requires-Dist: scoopy
Requires-Dist: beautifulsoup4
Requires-Dist: requests
Requires-Dist: scikit-learn
Requires-Dist: numpy
Requires-Dist: pandas
Requires-Dist: oa
Requires-Dist: config2py
Requires-Dist: dol
Requires-Dist: i2
Requires-Dist: argh
Requires-Dist: seaborn
Requires-Dist: matplotlib
